iflow_mcp_devizor_macos_notification_mcp-0.1.1.dist-info/licenses/LICENSE
macos_notification_mcp/__init__.py
macos_notification_mcp/server.py
iflow_mcp_devizor_macos_notification_mcp-0.1.1.dist-info/METADATA
iflow_mcp_devizor_macos_notification_mcp-0.1.1.dist-info/WHEEL
iflow_mcp_devizor_macos_notification_mcp-0.1.1.dist-info/entry_points.txt
iflow_mcp_devizor_macos_notification_mcp-0.1.1.dist-info/top_level.txt
iflow_mcp_devizor_macos_notification_mcp-0.1.1.dist-info/RECORD
